actdiag/__init__.py
actdiag/builder.py
actdiag/command.py
actdiag/drawer.py
actdiag/elements.py
actdiag/metrics.py
actdiag/parser.py
actdiag/plugins/__init__.py
actdiag/plugins/autolane.py
actdiag/tests/test_generate_diagram.py
actdiag/tests/test_rst_directives.py
actdiag/tests/VLGothic/LICENSE
actdiag/tests/VLGothic/LICENSE.en
actdiag/tests/VLGothic/LICENSE_E.mplus
actdiag/tests/VLGothic/LICENSE_J.mplus
actdiag/tests/VLGothic/VL-Gothic-Regular.ttf
actdiag/tests/diagrams/simple.diag
actdiag/utils/__init__.py
actdiag/utils/rst/__init__.py
actdiag/utils/rst/directives.py
actdiag/utils/rst/nodes.py
actdiag-3.0.0.dist-info/LICENSE
actdiag-3.0.0.dist-info/METADATA
actdiag-3.0.0.dist-info/WHEEL
actdiag-3.0.0.dist-info/entry_points.txt
actdiag-3.0.0.dist-info/top_level.txt
actdiag-3.0.0.dist-info/RECORD
